[ {
  "guide" : {
    "firstname" : "Per",
    "lastname" : "Hansen",
    "email" : "Per@hansen.no",
    "username" : null,
    "password" : null,
    "profileId" : 1500,
    "trips" : [ ]
  },
  "title" : "Fantastisk fjelltur",
  "location" : "Tromsø",
  "description" : "Opplev de majestetiske fjellene i Tromsø.",
  "price" : 500.0,
  "duration" : 3,
  "tripId" : 1,
  "date" : [ 2023, 6, 15 ],
  "reviews" : [ "Fantastisk tur!", "Vil dra igjen." ]
}, {
  "guide" : {
    "firstname" : "Per",
    "lastname" : "Hansen",
    "email" : "Per@hansen.no",
    "username" : null,
    "password" : null,
    "profileId" : 1500,
    "trips" : [ ]
  },
  "title" : "Midnattssol cruise",
  "location" : "Lofoten",
  "description" : "Se midnattssolen fra en luksuscruise i Lofoten.",
  "price" : 1200.0,
  "duration" : 2,
  "tripId" : 2,
  "date" : [ 2023, 7, 10 ],
  "reviews" : [ "Utrolig vakkert!", "Anbefales!" ]
}, {
  "guide" : {
    "firstname" : "Per",
    "lastname" : "Hansen",
    "email" : "Per@hansen.no",
    "username" : null,
    "password" : null,
    "profileId" : 1500,
    "trips" : [ ]
  },
  "title" : "Fantastiske Bergen",
  "location" : "Bergen",
  "description" : "Utforsk den vakre byen Bergen.",
  "price" : 300.0,
  "duration" : 1,
  "tripId" : 3,
  "date" : [ 2023, 5, 20 ],
  "reviews" : [ "Nydelig by!", "Fin tur." ]
}, {
  "guide" : {
    "firstname" : "Per",
    "lastname" : "Hansen",
    "email" : "Per@hansen.no",
    "username" : null,
    "password" : null,
    "profileId" : 1500,
    "trips" : [ ]
  },
  "title" : "Gåtur i norsk fjell",
  "location" : "Geilo",
  "description" : "Utforsk den norske naturen til fots.",
  "price" : 600.0,
  "duration" : 4,
  "tripId" : 4,
  "date" : [ 2023, 8, 12 ],
  "reviews" : [ "Flinke guider!", "Utrolig natur." ]
}, {
  "guide" : {
    "firstname" : "Per",
    "lastname" : "Hansen",
    "email" : "Per@hansen.no",
    "username" : null,
    "password" : null,
    "profileId" : 1500,
    "trips" : [ ]
  },
  "title" : "Spektakulært nordlys",
  "location" : "Alta",
  "description" : "Opplev det spektakulære nordlyset i Alta.",
  "price" : 800.0,
  "duration" : 2,
  "tripId" : 5,
  "date" : [ 2023, 11, 25 ],
  "reviews" : [ "Magisk!", "Enestående opplevelse." ]
}, {
  "guide" : {
    "firstname" : "Per",
    "lastname" : "Hansen",
    "email" : "Per@hansen.no",
    "username" : null,
    "password" : null,
    "profileId" : 1500,
    "trips" : [ ]
  },
  "title" : "Fjelltur i Jotunheimen",
  "location" : "Jotunheimen",
  "description" : "En flott fjelltur i Jotunheimen.",
  "price" : 500.0,
  "duration" : 3,
  "tripId" : 6,
  "date" : [ 2023, 6, 15 ],
  "reviews" : [ "Fantastisk tur!", "Anbefales!" ]
}, {
  "guide" : {
    "firstname" : "Per",
    "lastname" : "Hansen",
    "email" : "Per@hansen.no",
    "username" : null,
    "password" : null,
    "profileId" : 1500,
    "trips" : [ ]
  },
  "title" : "Skitur i Hemsedal",
  "location" : "Hemsedal",
  "description" : "En herlig skitur i Hemsedal.",
  "price" : 600.0,
  "duration" : 2,
  "tripId" : 7,
  "date" : [ 2023, 2, 15 ],
  "reviews" : [ "Utrolig gøy!", "Skal definitivt tilbake neste år." ]
}, {
  "guide" : {
    "firstname" : "Per",
    "lastname" : "Hansen",
    "email" : "Per@hansen.no",
    "username" : null,
    "password" : null,
    "profileId" : 1500,
    "trips" : [ ]
  },
  "title" : "Båttur i Lofoten",
  "location" : "Lofoten",
  "description" : "En fantastisk båttur rundt de vakre øyene i Lofoten.",
  "price" : 700.0,
  "duration" : 4,
  "tripId" : 8,
  "date" : [ 2023, 7, 10 ],
  "reviews" : [ "Fantastisk opplevelse!", "Lofoten er utrolig vakkert." ]
}, {
  "guide" : {
    "firstname" : "Per",
    "lastname" : "Hansen",
    "email" : "Per@hansen.no",
    "username" : null,
    "password" : null,
    "profileId" : 1500,
    "trips" : [ ]
  },
  "title" : "Sykkeltur i Geiranger",
  "location" : "Geiranger",
  "description" : "En uforglemmelig sykkeltur gjennom den storslåtte naturen i Geiranger.",
  "price" : 400.0,
  "duration" : 1,
  "tripId" : 9,
  "date" : [ 2023, 5, 20 ],
  "reviews" : [ "Sykkelturen var en drøm!", "Kan ikke vente med å gjøre dette igjen." ]
} ]